hypercli/__init__.py
hypercli/core.py
hypercli-2.0.8.dist-info/LICENSE
hypercli-2.0.8.dist-info/METADATA
hypercli-2.0.8.dist-info/WHEEL
hypercli-2.0.8.dist-info/RECORD
