Metadata-Version: 2.3
Name: hypercli
Version: 2.0.8
Summary: Generate enhanced menu-driven CLI programs with ease.
Author: hyperoot
Author-email: rajesh@proton.me
Requires-Python: >=3.12,<4.0
Classifier: Programming Language :: Python :: 3
Classifier: Programming Language :: Python :: 3.12
Classifier: Programming Language :: Python :: 3.13
Requires-Dist: cairosvg (>=2.7.1,<3.0.0)
Requires-Dist: pillow (>=11.1.0,<12.0.0)
Requires-Dist: pyfiglet (>=1.0.2,<2.0.0)
Requires-Dist: rich (>=13.7.1,<14.0.0)
Requires-Dist: termcolor (>=2.4.0,<3.0.0)
